dash_qrcode/8efdb42-async-QRCode-wps-hmr.js
dash_qrcode/8efdb42-async-QRCode-wps-hmr.js.map
dash_qrcode/8efdb42-wps-hmr.json
dash_qrcode/QRCode.py
dash_qrcode/__init__.py
dash_qrcode/_imports_.py
dash_qrcode/async-QRCode.js
dash_qrcode/async-QRCode.js.LICENSE.txt
dash_qrcode/async-QRCode.js.map
dash_qrcode/dash_qrcode.min.js
dash_qrcode/dash_qrcode.min.js.map
dash_qrcode/metadata.json
dash_qrcode/output.js
dash_qrcode/output.js.map
dash_qrcode/package-info.json
dash_qrcode-0.0.1.dist-info/LICENSE
dash_qrcode-0.0.1.dist-info/METADATA
dash_qrcode-0.0.1.dist-info/WHEEL
dash_qrcode-0.0.1.dist-info/top_level.txt
dash_qrcode-0.0.1.dist-info/RECORD
